README.md
setup.py
stethoscope/__init__.py
torch_stethoscope.egg-info/PKG-INFO
torch_stethoscope.egg-info/SOURCES.txt
torch_stethoscope.egg-info/dependency_links.txt
torch_stethoscope.egg-info/top_level.txt