Metadata-Version: 2.1
Name: torch-stethoscope
Version: 0.0.1
Summary: Automatic deep learning research report generator
Home-page: UNKNOWN
Author: Benoit Anctil-Robitaille
Author-email: benoit.anctil-robitaille.1@ens.etsmtl.ca
License: MIT
Platform: UNKNOWN
Classifier: License :: OSI Approved :: MIT License
Classifier: Programming Language :: Python :: 3
Classifier: Programming Language :: Python :: 3.7
